dnr_api/__init__.py
dnr_api/admin_dams.py
dnr_api/admin_dams_test.py
dnr_api/admin_field_investigation.py
dnr_api/admin_field_investigation_test.py
dnr_api/admin_floodplain.py
dnr_api/admin_floodplain_test.py
dnr_api/admin_pwap.py
dnr_api/admin_pwap_test.py
dnr_api/admin_water_rights.py
dnr_api/admin_water_rights_test.py
dnr_api/admin_water_use.py
dnr_api/admin_water_use_test.py
dnr_api/admin_wells.py
dnr_api/admin_wells_test.py
dnr_api/api.py
dnr_api/api_test.py
dnr_api/config.py
dnr_api/config_test.py
dnr_api/dams.py
dnr_api/dams_test.py
dnr_api/water_rights.py
dnr_api/water_rights_test.py
dnr_api/wells.py
dnr_api/wells_test.py
dnr_api-0.1.0.dist-info/METADATA
dnr_api-0.1.0.dist-info/WHEEL
dnr_api-0.1.0.dist-info/entry_points.txt
dnr_api-0.1.0.dist-info/top_level.txt
dnr_api-0.1.0.dist-info/RECORD
