Metadata-Version: 2.1
Name: dnr-api
Version: 0.1.0
Author: Sparrow Computing
Author-email: ben@sparrow.dev
Requires-Dist: fire
Requires-Dist: pandas
Requires-Dist: requests
Requires-Dist: tqdm
Provides-Extra: dev
Requires-Dist: black ; extra == 'dev'
Requires-Dist: isort ; extra == 'dev'
Requires-Dist: jupyter ; extra == 'dev'
Requires-Dist: myst-parser ; extra == 'dev'
Requires-Dist: pydocstyle ; extra == 'dev'
Requires-Dist: pylint ; extra == 'dev'
Requires-Dist: pytest ; extra == 'dev'
Requires-Dist: pytest-cov ; extra == 'dev'
Requires-Dist: requests-mock ; extra == 'dev'
Requires-Dist: sphinx ; extra == 'dev'
Requires-Dist: sphinx-rtd-theme ; extra == 'dev'
Requires-Dist: tox ; extra == 'dev'
